pytts/__init__.py
pytts/voicerss/__init__.py
pytts/voicerss/codecs.py
pytts/voicerss/formats.py
pytts/voicerss/languages.py
pytts/voicerss/voices.py
swisscore_pyTTS-1.0.0.dist-info/LICENSE
swisscore_pyTTS-1.0.0.dist-info/METADATA
swisscore_pyTTS-1.0.0.dist-info/WHEEL
swisscore_pyTTS-1.0.0.dist-info/top_level.txt
swisscore_pyTTS-1.0.0.dist-info/RECORD
