Metadata-Version: 2.1
Name: swisscore-pyTTS
Version: 1.0.0
Summary: UNKNOWN
Home-page: UNKNOWN
Author: SwissCorePy
Author-email: swisscore.py@gmail.com
License: gpl-3.0
Platform: UNKNOWN
Classifier: Programming Language :: Python :: 3
Classifier: Programming Language :: Python :: 3 :: Only
Classifier: Programming Language :: Python :: 3.10
Classifier: Development Status :: 5 - Production/Stable
Classifier: Environment :: Console
Classifier: License :: OSI Approved :: GNU General Public License v3 (GPLv3)
Requires-Python: >=3.10
License-File: LICENSE
Requires-Dist: requests
